textual_cogs/__init__.py
textual_cogs/icons.py
textual_cogs/labels.py
textual_cogs/dialogs/__init__.py
textual_cogs/dialogs/message_dialog.py
textual_cogs/dialogs/quit_dialog.py
textual_cogs/dialogs/save_dialog.py
textual_cogs/dialogs/single_choice_dialog.py
textual_cogs/dialogs/single_color_picker_dialog.py
textual_cogs/dialogs/text_entry_dialog.py
textual_cogs-0.0.3.dist-info/LICENSE
textual_cogs-0.0.3.dist-info/METADATA
textual_cogs-0.0.3.dist-info/WHEEL
textual_cogs-0.0.3.dist-info/top_level.txt
textual_cogs-0.0.3.dist-info/RECORD
