Metadata-Version: 2.1
Name: textual-cogs
Version: 0.0.3
Summary: Dialogs for use with the Textual package.
Author-email: Mike Driscoll <mike@pythonlibrary.org>
Project-URL: Homepage, https://github.com/driscollis/textual-cogs
Project-URL: Issues, https://github.com/driscollis/textual-cogs/issues
Classifier: Development Status :: 4 - Beta
Classifier: License :: OSI Approved :: MIT License
Classifier: Environment :: Console
Classifier: Intended Audience :: Developers
Classifier: Operating System :: Microsoft :: Windows :: Windows 10
Classifier: Operating System :: Microsoft :: Windows :: Windows 11
Classifier: Operating System :: MacOS
Classifier: Operating System :: POSIX :: Linux
Classifier: Programming Language :: Python :: 3.8
Classifier: Programming Language :: Python :: 3.9
Classifier: Programming Language :: Python :: 3.10
Classifier: Programming Language :: Python :: 3.11
Classifier: Programming Language :: Python :: 3.12
Classifier: Typing :: Typed
License-File: LICENSE
